stakefish_web3_utils-0.10.2.dist-info/licenses/LICENSE.md
web3_utils/__init__.py
web3_utils/async_beacon.py
web3_utils/calculate_max_fees.py
web3_utils/compute_time_at_slot.py
web3_utils/convert_to_standard_notation.py
web3_utils/current_utc_timestamp.py
web3_utils/divide_chunks.py
web3_utils/gitlab.py
web3_utils/gwei_to_wei.py
web3_utils/hash_event_param.py
web3_utils/is_null_address.py
web3_utils/load_public_keys_from_files.py
web3_utils/normalize_address.py
web3_utils/retryable_eth_module.py
web3_utils/split_validator_pubkey_bytes.py
stakefish_web3_utils-0.10.2.dist-info/METADATA
stakefish_web3_utils-0.10.2.dist-info/WHEEL
stakefish_web3_utils-0.10.2.dist-info/top_level.txt
stakefish_web3_utils-0.10.2.dist-info/RECORD
