Metadata-Version: 2.4
Name: stakefish-web3-utils
Version: 0.10.2
Summary: Stakefish’s web3 utils for Python
Home-page: https://github.com/stakefish/web3-utils
Author: Michal Baranowski <mbaranovski@stake.fish>, Mateusz Sokola <mateusz@stake.fish>
Classifier: Development Status :: 5 - Production/Stable
Classifier: Intended Audience :: Developers
Classifier: Natural Language :: English
Classifier: Programming Language :: Python :: 3.9
Requires-Python: >=3.9
License-File: LICENSE.md
Requires-Dist: web3
Requires-Dist: tenacity
Requires-Dist: python-gitlab
Provides-Extra: tests
Requires-Dist: eth-brownie; extra == "tests"
Requires-Dist: pytest-asyncio; extra == "tests"
Requires-Dist: pytest-mock; extra == "tests"
Dynamic: license-file
